apispec/__init__.py
apispec/core.py
apispec/exceptions.py
apispec/plugin.py
apispec/py.typed
apispec/utils.py
apispec/yaml_utils.py
apispec/ext/__init__.py
apispec/ext/marshmallow/__init__.py
apispec/ext/marshmallow/common.py
apispec/ext/marshmallow/field_converter.py
apispec/ext/marshmallow/openapi.py
apispec/ext/marshmallow/schema_resolver.py
apispec-6.4.0.dist-info/LICENSE
apispec-6.4.0.dist-info/METADATA
apispec-6.4.0.dist-info/WHEEL
apispec-6.4.0.dist-info/top_level.txt
apispec-6.4.0.dist-info/RECORD
